[
  {
    "id": "771e8d43-e067-5f44-9281-acd440573526",
    "dataType": "wifi",
    "dataSource": "gov-data",
    "category": "洽公場所",
    "name": "彰化縣埔鹽鄉衛生所",
    "lat": 24.000364,
    "lng": 120.463213,
    "address": "516彰化縣埔鹽鄉員鹿路二段58號",
    "ssid": "iTaiwan",
    "authType": "portal"
  },
  {
    "id": "07401974-b132-538d-9af6-75eb491fd7d7",
    "dataType": "wifi",
    "dataSource": "gov-data",
    "category": "洽公場所",
    "name": "彰化縣埔鹽鄉公所",
    "lat": 24.000417,
    "lng": 120.463647,
    "address": "516彰化縣埔鹽鄉中正路192號",
    "ssid": "iTaiwan",
    "authType": "portal"
  },
  {
    "id": "6ba1587e-2581-591b-9599-8aff21102ebd",
    "dataType": "wifi",
    "dataSource": "gov-data",
    "category": "洽公場所",
    "name": "彰化縣埔鹽鄉公所服務台",
    "lat": 24.000417,
    "lng": 120.463647,
    "address": "516彰化縣埔鹽鄉中正路192號",
    "ssid": "iTaiwan",
    "authType": "portal"
  },
  {
    "id": "ba0f0d92-2387-5e3c-9648-b93643e99b15",
    "dataType": "wifi",
    "dataSource": "gov-data",
    "category": "文教館所",
    "name": "彰化縣埔鹽鄉立圖書館",
    "lat": 24.000593,
    "lng": 120.463091,
    "address": "516彰化縣埔鹽鄉好修村員鹿路二段60號",
    "ssid": "iTaiwan",
    "authType": "portal"
  },
  {
    "id": "3b43a221-b3b5-59eb-90d6-6746a61fbd0c",
    "dataType": "wifi",
    "dataSource": "gov-data",
    "category": "洽公場所",
    "name": "彰化縣警察局鹿港分局外中派出所",
    "lat": 24.017538,
    "lng": 120.47204,
    "address": "506彰化縣福興鄉外中村外中街237號",
    "ssid": "iTaiwan",
    "authType": "portal"
  }
]
