[
  {
    "id": "73f2df55-35d6-5158-9a4f-0813d16613e1",
    "dataType": "wifi",
    "dataSource": "gov-data",
    "category": "洽公場所",
    "name": "高雄市府郵局",
    "lat": 22.620307,
    "lng": 120.312091,
    "address": "802高雄市苓雅區四維三路2號",
    "ssid": "iTaiwan",
    "authType": "portal"
  },
  {
    "id": "95639657-c214-560c-b4f7-25c4a67b147d",
    "dataType": "wifi",
    "dataSource": "gov-data",
    "category": "洽公場所",
    "name": "臺灣銀行苓雅分行",
    "lat": 22.620547,
    "lng": 120.30437,
    "address": "802高雄市苓雅區青年一路261號",
    "ssid": "iTaiwan",
    "authType": "portal"
  },
  {
    "id": "48df3d55-2aee-5bd3-9a8c-0aef2e46b94a",
    "dataType": "wifi",
    "dataSource": "gov-data",
    "category": "洽公場所",
    "name": "高雄市政府",
    "lat": 22.620958,
    "lng": 120.311792,
    "address": "802高雄市苓雅區四維三路2號",
    "ssid": "iTaiwan",
    "authType": "portal"
  },
  {
    "id": "edba69fd-782a-5e7b-ba43-845c10752aab",
    "dataType": "wifi",
    "dataSource": "gov-data",
    "category": "洽公場所",
    "name": "財政部高雄國稅局苓雅稽徵所",
    "lat": 22.621771,
    "lng": 120.312154,
    "address": "802高雄市苓雅區民權一路85號8樓",
    "ssid": "iTaiwan",
    "authType": "portal"
  },
  {
    "id": "9edccc68-4322-5a0e-add6-70ac16518668",
    "dataType": "wifi",
    "dataSource": "gov-data",
    "category": "洽公場所",
    "name": "高雄市苓雅區戶政事務所所本部",
    "lat": 22.621778,
    "lng": 120.312229,
    "address": "802高雄市苓雅區民權一路85號2樓",
    "ssid": "iTaiwan",
    "authType": "portal"
  },
  {
    "id": "ccf61957-4b24-5ce6-8e40-c56ae585c835",
    "dataType": "wifi",
    "dataSource": "gov-data",
    "category": "洽公場所",
    "name": "高雄市苓雅區公所",
    "lat": 22.62185,
    "lng": 120.312197,
    "address": "802高雄市苓雅區民權一路85號",
    "ssid": "iTaiwan",
    "authType": "portal"
  },
  {
    "id": "56085fb5-7af9-5be8-b89d-1866c7170ac4",
    "dataType": "wifi",
    "dataSource": "gov-data",
    "category": "洽公場所",
    "name": "高雄新田郵局",
    "lat": 22.622207,
    "lng": 120.303833,
    "address": "800高雄市新興區新田路133號",
    "ssid": "iTaiwan",
    "authType": "portal"
  },
  {
    "id": "053e3d89-fb86-51ed-8505-5d8175cb0530",
    "dataType": "wifi",
    "dataSource": "gov-data",
    "category": "洽公場所",
    "name": "華南商業銀行光華分行",
    "lat": 22.622248,
    "lng": 120.316448,
    "address": "802高雄市苓雅區光華一路148-19號",
    "ssid": "iTaiwan",
    "authType": "portal"
  },
  {
    "id": "d1cf4774-d089-566b-bfa5-a100774a3984",
    "dataType": "wifi",
    "dataSource": "gov-data",
    "category": "其他",
    "name": "高雄市新興區新正氣社區發展協會",
    "lat": 22.622796,
    "lng": 120.307179,
    "address": "800高雄市新興區正氣里忠孝一路32號",
    "ssid": "iTaiwan",
    "authType": "portal"
  },
  {
    "id": "7d111bf3-2d52-501c-8753-1c2f7bde9957",
    "dataType": "wifi",
    "dataSource": "gov-data",
    "category": "洽公場所",
    "name": "高雄文化中心郵局",
    "lat": 22.622842,
    "lng": 120.316225,
    "address": "802高雄市苓雅區光華一路148-30號",
    "ssid": "iTaiwan",
    "authType": "portal"
  },
  {
    "id": "182f40f9-bcfd-5640-a8cd-758a29ee43f6",
    "dataType": "wifi",
    "dataSource": "gov-data",
    "category": "洽公場所",
    "name": "中油公司高雄市新興區林森二路站",
    "lat": 22.623071,
    "lng": 120.305714,
    "address": "800高雄市新興區新田路82號",
    "ssid": "iTaiwan",
    "authType": "portal"
  },
  {
    "id": "f30175a1-2b5b-57cb-9e81-b64fbdbac45c",
    "dataType": "wifi",
    "dataSource": "gov-data",
    "category": "旅遊景點",
    "name": "城市光廊(公車站西)",
    "lat": 22.623365,
    "lng": 120.30093,
    "address": "801高雄市前金區中山二路與五福三路公車站",
    "ssid": "iTaiwan",
    "authType": "portal"
  },
  {
    "id": "a7c1e493-8bec-54e9-8599-ed8aa4a4e8f4",
    "dataType": "wifi",
    "dataSource": "gov-data",
    "category": "洽公場所",
    "name": "財政部高雄國稅局",
    "lat": 22.623734,
    "lng": 120.317451,
    "address": "802高雄市苓雅區廣州一街148號",
    "ssid": "iTaiwan",
    "authType": "portal"
  },
  {
    "id": "a4dd3f31-bb46-53d0-9171-dbfbf3f03cca",
    "dataType": "wifi",
    "dataSource": "gov-data",
    "category": "洽公場所",
    "name": "內政部營建署南區工程處1樓大廳",
    "lat": 22.624753,
    "lng": 120.305095,
    "address": "800高雄市新興區五福二路200號",
    "ssid": "iTaiwan",
    "authType": "portal"
  },
  {
    "id": "72be3ed0-d117-5ea3-875a-ecd29873c1bd",
    "dataType": "wifi",
    "dataSource": "gov-data",
    "category": "其他",
    "name": "內政部營建署南區工程處3F(會議室)",
    "lat": 22.624753,
    "lng": 120.305095,
    "address": "800高雄市新興區五福二路200號",
    "ssid": "iTaiwan",
    "authType": "portal"
  },
  {
    "id": "eb0b4c6c-04bb-5f34-b36c-03c7df74870c",
    "dataType": "wifi",
    "dataSource": "gov-data",
    "category": "其他",
    "name": "內政部營建署南區工程處7F(會議室)",
    "lat": 22.624753,
    "lng": 120.305095,
    "address": "800高雄市新興區五福二路200號",
    "ssid": "iTaiwan",
    "authType": "portal"
  },
  {
    "id": "a6938cc2-cd52-52fb-9bf3-149baf024a12",
    "dataType": "wifi",
    "dataSource": "gov-data",
    "category": "洽公場所",
    "name": "內政部營建署城鄉發展分署南區規劃隊",
    "lat": 22.624762,
    "lng": 120.305083,
    "address": "800高雄市新興區五福二路200號5樓",
    "ssid": "iTaiwan",
    "authType": "portal"
  },
  {
    "id": "9a5508e3-f2de-5971-9188-b49315ed6960",
    "dataType": "wifi",
    "dataSource": "gov-data",
    "category": "洽公場所",
    "name": "高雄青年郵局",
    "lat": 22.624956,
    "lng": 120.308353,
    "address": "800高雄市新興區復興二路171號",
    "ssid": "iTaiwan",
    "authType": "portal"
  },
  {
    "id": "ce231ea6-99b4-57e2-aadc-d546a2981db4",
    "dataType": "wifi",
    "dataSource": "gov-data",
    "category": "洽公場所",
    "name": "兆豐國際商銀五福分行",
    "lat": 22.625695,
    "lng": 120.308332,
    "address": "800高雄市新興區五福二路82號",
    "ssid": "iTaiwan",
    "authType": "portal"
  },
  {
    "id": "a2ffc9df-1679-58e1-a23d-93a68fceab76",
    "dataType": "wifi",
    "dataSource": "gov-data",
    "category": "文教館所",
    "name": "高雄市政府文化局",
    "lat": 22.625771,
    "lng": 120.318322,
    "address": "802高雄市苓雅區五福一路67號",
    "ssid": "iTaiwan",
    "authType": "portal"
  },
  {
    "id": "8dce146e-4646-50f3-a1f8-2476454c4b0c",
    "dataType": "wifi",
    "dataSource": "gov-data",
    "category": "其他",
    "name": "財團法人台灣基督徒環球佈道團",
    "lat": 22.625798,
    "lng": 120.30798,
    "address": "800高雄市新興區永寧里復興二路189號",
    "ssid": "iTaiwan",
    "authType": "portal"
  },
  {
    "id": "30c5a236-a3e1-54ea-b2a7-03857901eff6",
    "dataType": "wifi",
    "dataSource": "gov-data",
    "category": "文教館所",
    "name": "高雄市文化中心(五福一路門口公話)",
    "lat": 22.625808,
    "lng": 120.318142,
    "address": "802高雄市苓雅區五福一路67號",
    "ssid": "iTaiwan",
    "authType": "portal"
  },
  {
    "id": "0dccaf65-98b3-508d-a1fd-f4d4a697acdd",
    "dataType": "wifi",
    "dataSource": "gov-data",
    "category": "文教館所",
    "name": "高雄市文化中心(至德堂公話)",
    "lat": 22.625808,
    "lng": 120.318142,
    "address": "802高雄市苓雅區五福一路67號",
    "ssid": "iTaiwan",
    "authType": "portal"
  },
  {
    "id": "413e5f7e-27ec-5472-9dcf-a7f379cded7d",
    "dataType": "wifi",
    "dataSource": "gov-data",
    "category": "文教館所",
    "name": "高雄市文化中心(前廳公話)",
    "lat": 22.625808,
    "lng": 120.318142,
    "address": "802高雄市苓雅區五福一路67號",
    "ssid": "iTaiwan",
    "authType": "portal"
  },
  {
    "id": "4c48511b-3d2b-5b05-bc99-cbe589e208a8",
    "dataType": "wifi",
    "dataSource": "gov-data",
    "category": "文教館所",
    "name": "高雄市文化中心(至真三館)",
    "lat": 22.625808,
    "lng": 120.318142,
    "address": "802高雄市苓雅區五福一路67號",
    "ssid": "iTaiwan",
    "authType": "portal"
  },
  {
    "id": "d86472e6-3c60-59e5-aa09-a076f6c6c084",
    "dataType": "wifi",
    "dataSource": "gov-data",
    "category": "文教館所",
    "name": "高雄市文化中心(警衛室公話)",
    "lat": 22.625808,
    "lng": 120.318142,
    "address": "802高雄市苓雅區五福一路67號",
    "ssid": "iTaiwan",
    "authType": "portal"
  },
  {
    "id": "794949f8-4acc-54b7-a9a4-cc5be39d7f08",
    "dataType": "wifi",
    "dataSource": "gov-data",
    "category": "文教館所",
    "name": "高雄市文化中心(圖書館公話)",
    "lat": 22.625808,
    "lng": 120.318142,
    "address": "802高雄市苓雅區五福一路67號",
    "ssid": "iTaiwan",
    "authType": "portal"
  },
  {
    "id": "03d4aed9-86e3-5918-b0be-b563b484dfbd",
    "dataType": "wifi",
    "dataSource": "gov-data",
    "category": "文教館所",
    "name": "高雄市立圖書館高雄市文化中心分館",
    "lat": 22.626608,
    "lng": 120.317974,
    "address": "802高雄市苓雅區五福一路67號",
    "ssid": "iTaiwan",
    "authType": "portal"
  },
  {
    "id": "c4ef6347-7b46-5597-b210-542828692e1b",
    "dataType": "wifi",
    "dataSource": "gov-data",
    "category": "文教館所",
    "name": "高雄市立圖書館新興民眾閱覽室",
    "lat": 22.627272,
    "lng": 120.306843,
    "address": "800高雄市新興區民生一路271號",
    "ssid": "iTaiwan",
    "authType": "portal"
  },
  {
    "id": "04032a3d-76a9-5328-90bb-c50a42b5c9bc",
    "dataType": "wifi",
    "dataSource": "gov-data",
    "category": "其他",
    "name": "國防部高雄福利站服務台1",
    "lat": 22.628292,
    "lng": 120.308091,
    "address": "800高雄市新興區復興一路6號",
    "ssid": "iTaiwan",
    "authType": "portal"
  },
  {
    "id": "4aed74b1-5356-55fa-85af-fa49c9b071c9",
    "dataType": "wifi",
    "dataSource": "gov-data",
    "category": "其他",
    "name": "社團法人高雄市善護關愛協會(新興站)",
    "lat": 22.629767,
    "lng": 120.311101,
    "address": "800高雄市新興區光耀里黃海街62號一樓",
    "ssid": "iTaiwan",
    "authType": "portal"
  },
  {
    "id": "f9693022-cca4-5302-a309-c19d27caad85",
    "dataType": "wifi",
    "dataSource": "gov-data",
    "category": "其他",
    "name": "財團法人台灣聖公會(高雄)",
    "lat": 22.630007,
    "lng": 120.306102,
    "address": "800高雄市新興區德政里忠孝一路262號三樓",
    "ssid": "iTaiwan",
    "authType": "portal"
  },
  {
    "id": "aa95e1c6-b959-5c08-889d-67f5ad753cee",
    "dataType": "wifi",
    "dataSource": "gov-data",
    "category": "其他",
    "name": "中華民國健康生活管理促進產業協會(東坡站)",
    "lat": 22.630262,
    "lng": 120.30229,
    "address": "800高雄市新興區東坡里中山一路78之3號",
    "ssid": "iTaiwan",
    "authType": "portal"
  },
  {
    "id": "409a40ae-e8f2-5b4d-b8b5-72228aae9904",
    "dataType": "wifi",
    "dataSource": "gov-data",
    "category": "洽公場所",
    "name": "第一商業銀行(五福分行)",
    "lat": 22.630272,
    "lng": 120.314618,
    "address": "802高雄市苓雅區中正二路161號",
    "ssid": "iTaiwan",
    "authType": "portal"
  },
  {
    "id": "216a8333-4be5-59f9-ac89-ff00ec6d5b82",
    "dataType": "wifi",
    "dataSource": "gov-data",
    "category": "洽公場所",
    "name": "財政部國有財產署南區分署18樓民眾等候區",
    "lat": 22.630354,
    "lng": 120.309898,
    "address": "800高雄市新興區中正三路25號18樓",
    "ssid": "iTaiwan",
    "authType": "portal"
  },
  {
    "id": "b70f8eb8-033c-575f-bd11-72ca1a051bf4",
    "dataType": "wifi",
    "dataSource": "gov-data",
    "category": "洽公場所",
    "name": "勞動部勞動力發展署高屏澎東分署高屏澎東區銀髮人才資源中心洽公服務櫃台",
    "lat": 22.630438,
    "lng": 120.318793,
    "address": "802高雄市苓雅區中正一路306號2樓",
    "ssid": "iTaiwan",
    "authType": "portal"
  },
  {
    "id": "2becd8ed-0a10-5252-b124-c895cd26ff93",
    "dataType": "wifi",
    "dataSource": "gov-data",
    "category": "其他",
    "name": "社團法人高雄市善護關愛協會(善護站)-搬",
    "lat": 22.630496,
    "lng": 120.300035,
    "address": "800高雄市新興區大明里中正四路53號二樓之1",
    "ssid": "iTaiwan",
    "authType": "portal"
  },
  {
    "id": "40c849cc-551f-53a3-b5a8-85f5c63c9d69",
    "dataType": "wifi",
    "dataSource": "gov-data",
    "category": "洽公場所",
    "name": "中國輸出入銀行高雄分行",
    "lat": 22.630545,
    "lng": 120.318468,
    "address": "802高雄市苓雅區中正二路74號8樓",
    "ssid": "iTaiwan",
    "authType": "portal"
  },
  {
    "id": "a24e1d90-5b95-54c2-9f1f-b5bc662bf977",
    "dataType": "wifi",
    "dataSource": "gov-data",
    "category": "洽公場所",
    "name": "高雄市稅捐稽徵處新興分處",
    "lat": 22.630549,
    "lng": 120.30952,
    "address": "800高雄市新興區中正三路25號1樓",
    "ssid": "iTaiwan",
    "authType": "portal"
  },
  {
    "id": "e6bb99b3-eefd-50fb-89fb-96980db0de41",
    "dataType": "wifi",
    "dataSource": "gov-data",
    "category": "洽公場所",
    "name": "司法院(高雄地方法院-第二辦公大樓)",
    "lat": 22.630751,
    "lng": 120.31004,
    "address": "800高雄市新興區中正三路25號",
    "ssid": "iTaiwan",
    "authType": "portal"
  },
  {
    "id": "78f91830-e462-5ac9-9682-65fcd7dadc3d",
    "dataType": "wifi",
    "dataSource": "gov-data",
    "category": "洽公場所",
    "name": "上海商銀高雄分行",
    "lat": 22.630879,
    "lng": 120.307981,
    "address": "800高雄市新興區中正三路61號",
    "ssid": "iTaiwan",
    "authType": "portal"
  },
  {
    "id": "33a6e14c-8b76-5de3-a6e3-0bc957c5fe74",
    "dataType": "wifi",
    "dataSource": "gov-data",
    "category": "其他",
    "name": "第一金證券新興分公司",
    "lat": 22.630884,
    "lng": 120.301065,
    "address": "800高雄市新興區中正四路17號3樓",
    "ssid": "iTaiwan",
    "authType": "portal"
  },
  {
    "id": "bb201357-2171-51d7-bb15-d3a9d6460a2d",
    "dataType": "wifi",
    "dataSource": "gov-data",
    "category": "洽公場所",
    "name": "第一商業銀行新興分行",
    "lat": 22.63089,
    "lng": 120.301051,
    "address": "800高雄市新興區中正四路17號",
    "ssid": "iTaiwan",
    "authType": "portal"
  },
  {
    "id": "c5a985b4-aebf-59a6-af14-9bab6f96df07",
    "dataType": "wifi",
    "dataSource": "gov-data",
    "category": "洽公場所",
    "name": "新興郵局-1",
    "lat": 22.631012,
    "lng": 120.30416,
    "address": "800高雄市新興區中正三路177、179號",
    "ssid": "iTaiwan",
    "authType": "portal"
  },
  {
    "id": "5a073844-dd3e-5a89-99a1-dd8fff6fd98e",
    "dataType": "wifi",
    "dataSource": "gov-data",
    "category": "洽公場所",
    "name": "新興郵局-2",
    "lat": 22.631012,
    "lng": 120.30416,
    "address": "800高雄市新興區中正三路177、179號",
    "ssid": "iTaiwan",
    "authType": "portal"
  },
  {
    "id": "e328df0b-71f4-5d72-b5af-8c53131d74d4",
    "dataType": "wifi",
    "dataSource": "gov-data",
    "category": "洽公場所",
    "name": "高雄市政府地政局新興地政事務所",
    "lat": 22.631072,
    "lng": 120.310021,
    "address": "800高雄市新興區中正三路34號6樓",
    "ssid": "iTaiwan",
    "authType": "portal"
  },
  {
    "id": "776485c0-98f9-55ee-bf3d-68ba297666eb",
    "dataType": "wifi",
    "dataSource": "gov-data",
    "category": "洽公場所",
    "name": "財政部高雄國稅局新興稽徵所",
    "lat": 22.631081,
    "lng": 120.309992,
    "address": "800高雄市新興區中正三路34號8樓",
    "ssid": "iTaiwan",
    "authType": "portal"
  },
  {
    "id": "995fb4ec-d767-5f15-a4c6-c630c88e9a2c",
    "dataType": "wifi",
    "dataSource": "gov-data",
    "category": "文教館所",
    "name": "高雄市立圖書館新興分館",
    "lat": 22.631163,
    "lng": 120.309879,
    "address": "800高雄市新興區中正三路34號3樓",
    "ssid": "iTaiwan",
    "authType": "portal"
  },
  {
    "id": "f665899c-76bf-53d7-a3c7-2e0c94b62e82",
    "dataType": "wifi",
    "dataSource": "gov-data",
    "category": "洽公場所",
    "name": "高雄市新興區公所",
    "lat": 22.631253,
    "lng": 120.309992,
    "address": "800高雄市新興區中東里中正三路34號4樓",
    "ssid": "iTaiwan",
    "authType": "portal"
  },
  {
    "id": "5ed46d07-9e59-5859-8237-451d5e2d95f1",
    "dataType": "wifi",
    "dataSource": "gov-data",
    "category": "洽公場所",
    "name": "高雄市新興區戶政事務所",
    "lat": 22.631322,
    "lng": 120.309949,
    "address": "800高雄市新興區中正三路34號2樓",
    "ssid": "iTaiwan",
    "authType": "portal"
  },
  {
    "id": "004913c6-c859-5096-9666-2b2a36f1c73c",
    "dataType": "wifi",
    "dataSource": "gov-data",
    "category": "洽公場所",
    "name": "臺灣土地銀行中正分行",
    "lat": 22.631444,
    "lng": 120.304072,
    "address": "800高雄市新興區中正三路158號",
    "ssid": "iTaiwan",
    "authType": "portal"
  },
  {
    "id": "df34fee5-584d-5c27-96c8-469161f6c261",
    "dataType": "wifi",
    "dataSource": "gov-data",
    "category": "洽公場所",
    "name": "華南商業銀行新興分行",
    "lat": 22.632174,
    "lng": 120.301344,
    "address": "800高雄市新興區中山一路117號",
    "ssid": "iTaiwan",
    "authType": "portal"
  },
  {
    "id": "bf8443a4-cd32-5ddb-b717-39cafd347adf",
    "dataType": "wifi",
    "dataSource": "gov-data",
    "category": "洽公場所",
    "name": "華南商業銀行東高雄分行",
    "lat": 22.632622,
    "lng": 120.309343,
    "address": "800高雄市新興區六合一路78號",
    "ssid": "iTaiwan",
    "authType": "portal"
  },
  {
    "id": "b0c51718-7b08-5e43-bc12-b5f08a866584",
    "dataType": "wifi",
    "dataSource": "gov-data",
    "category": "洽公場所",
    "name": "農糧署南區分署高雄辦事處",
    "lat": 22.632788,
    "lng": 120.304348,
    "address": "800高雄市新興區六合一路113號",
    "ssid": "iTaiwan",
    "authType": "portal"
  },
  {
    "id": "4cd56e34-d02e-502e-b0ff-a825facd7f10",
    "dataType": "wifi",
    "dataSource": "gov-data",
    "category": "洽公場所",
    "name": "行政執行署高雄分署1樓等候區",
    "lat": 22.633524,
    "lng": 120.308548,
    "address": "800高雄市新興區復興一路80號",
    "ssid": "iTaiwan",
    "authType": "portal"
  },
  {
    "id": "f1db59f7-046a-5bf2-939f-da20261bd148",
    "dataType": "wifi",
    "dataSource": "gov-data",
    "category": "洽公場所",
    "name": "行政執行署高雄分署2樓等候區",
    "lat": 22.633524,
    "lng": 120.308548,
    "address": "800高雄市新興區復興一路80號",
    "ssid": "iTaiwan",
    "authType": "portal"
  },
  {
    "id": "2e5e7401-b641-5e2a-b02f-0460596ed58b",
    "dataType": "wifi",
    "dataSource": "gov-data",
    "category": "洽公場所",
    "name": "高雄順昌郵局",
    "lat": 22.633889,
    "lng": 120.314262,
    "address": "800高雄市新興區七賢一路104、106號",
    "ssid": "iTaiwan",
    "authType": "portal"
  },
  {
    "id": "a2163bd4-e44c-5ee7-8381-126024420d47",
    "dataType": "wifi",
    "dataSource": "gov-data",
    "category": "洽公場所",
    "name": "臺灣銀行新興分行",
    "lat": 22.63396,
    "lng": 120.313257,
    "address": "800高雄市新興區民族二路133號",
    "ssid": "iTaiwan",
    "authType": "portal"
  },
  {
    "id": "299d68ae-1ccb-55ab-885c-58c13eb6c774",
    "dataType": "wifi",
    "dataSource": "gov-data",
    "category": "洽公場所",
    "name": "臺灣土地銀行新興分行",
    "lat": 22.634608,
    "lng": 120.304076,
    "address": "800高雄市新興區七賢一路480號",
    "ssid": "iTaiwan",
    "authType": "portal"
  },
  {
    "id": "dbdfbbe6-aa48-5530-8eca-7121132793af",
    "dataType": "wifi",
    "dataSource": "gov-data",
    "category": "其他",
    "name": "社團法人高雄市天心慈善會",
    "lat": 22.634866,
    "lng": 120.30618,
    "address": "800高雄市新興區南港里忠孝一路417號",
    "ssid": "iTaiwan",
    "authType": "portal"
  },
  {
    "id": "b51db32d-f979-5ad5-b9c5-4837aad8204d",
    "dataType": "wifi",
    "dataSource": "gov-data",
    "category": "洽公場所",
    "name": "臺灣土地銀行建國分行",
    "lat": 22.635523,
    "lng": 120.316595,
    "address": "807高雄市三民區建國一路458號",
    "ssid": "iTaiwan",
    "authType": "portal"
  },
  {
    "id": "c7775c57-63b1-5fff-81bf-cff3a2ee5b04",
    "dataType": "wifi",
    "dataSource": "gov-data",
    "category": "洽公場所",
    "name": "國家通訊傳播委員會南區監理處服務中心",
    "lat": 22.636013,
    "lng": 120.310816,
    "address": "800高雄市新興區錦田路142號1樓",
    "ssid": "iTaiwan",
    "authType": "portal"
  },
  {
    "id": "85c64e5f-d3a2-5404-aee7-d3b80ce330d8",
    "dataType": "wifi",
    "dataSource": "gov-data",
    "category": "洽公場所",
    "name": "兆豐國際商銀新興分行",
    "lat": 22.636466,
    "lng": 120.302621,
    "address": "800高雄市新興區中山一路308號",
    "ssid": "iTaiwan",
    "authType": "portal"
  },
  {
    "id": "1333f53c-13e5-5b79-a0bc-bd6d315ef729",
    "dataType": "wifi",
    "dataSource": "gov-data",
    "category": "其他",
    "name": "康威藥局(三民)",
    "lat": 22.636886,
    "lng": 120.306369,
    "address": "807高雄市三民區港東里008鄰忠孝一路473巷1號",
    "ssid": "iTaiwan",
    "authType": "portal"
  },
  {
    "id": "45d26d46-8e03-5ca3-b769-82b06bb99f0f",
    "dataType": "wifi",
    "dataSource": "gov-data",
    "category": "洽公場所",
    "name": "高雄站前郵局",
    "lat": 22.638437,
    "lng": 120.301407,
    "address": "807高雄市三民區建國三路2-2號",
    "ssid": "iTaiwan",
    "authType": "portal"
  },
  {
    "id": "1c845c84-dc89-5b72-9140-88fd5a5cfe47",
    "dataType": "wifi",
    "dataSource": "gov-data",
    "category": "大眾運輸節點",
    "name": "臺鐵局民族站穿堂層（地下1樓）",
    "lat": 22.638761,
    "lng": 120.314871,
    "address": "807高雄市三民區博惠里14鄰凱旋一路260號",
    "ssid": "iTaiwan",
    "authType": "portal"
  },
  {
    "id": "19a91f0a-070e-56db-856a-d3f5ead29e41",
    "dataType": "wifi",
    "dataSource": "gov-data",
    "category": "大眾運輸節點",
    "name": "臺鐵局民族站第1月台5車位置",
    "lat": 22.638761,
    "lng": 120.314871,
    "address": "807高雄市三民區博惠里14鄰凱旋一路260號",
    "ssid": "iTaiwan",
    "authType": "portal"
  },
  {
    "id": "e264089b-d538-59fe-bab3-19135ea2cb7e",
    "dataType": "wifi",
    "dataSource": "gov-data",
    "category": "大眾運輸節點",
    "name": "臺鐵局民族站第2月台8車位置",
    "lat": 22.638761,
    "lng": 120.314871,
    "address": "807高雄市三民區博惠里14鄰凱旋一路260號",
    "ssid": "iTaiwan",
    "authType": "portal"
  },
  {
    "id": "6b2c1bb9-4174-5e47-8733-e6b92acb0552",
    "dataType": "wifi",
    "dataSource": "gov-data",
    "category": "其他",
    "name": "社團法人高雄市燭光協會",
    "lat": 22.63946,
    "lng": 120.316925,
    "address": "807高雄市三民區安寧里九如一路899號",
    "ssid": "iTaiwan",
    "authType": "portal"
  },
  {
    "id": "05ef9617-f9eb-5ad2-bb60-8307e456feba",
    "dataType": "wifi",
    "dataSource": "gov-data",
    "category": "大眾運輸節點",
    "name": "臺鐵局高雄站東側大廳",
    "lat": 22.63962,
    "lng": 120.302109,
    "address": "807高雄市三民區建國二路318號",
    "ssid": "iTaiwan",
    "authType": "portal"
  },
  {
    "id": "73ca8aa9-1176-5bdc-9938-f9819961305c",
    "dataType": "wifi",
    "dataSource": "gov-data",
    "category": "大眾運輸節點",
    "name": "臺鐵局高雄站西側大廳",
    "lat": 22.63962,
    "lng": 120.302109,
    "address": "807高雄市三民區建國二路318號",
    "ssid": "iTaiwan",
    "authType": "portal"
  },
  {
    "id": "a7994596-a5e1-5c03-a18c-7dca3b9e1f0f",
    "dataType": "wifi",
    "dataSource": "gov-data",
    "category": "大眾運輸節點",
    "name": "臺鐵局高雄站第2月台8車",
    "lat": 22.63962,
    "lng": 120.302109,
    "address": "807高雄市三民區建國二路318號",
    "ssid": "iTaiwan",
    "authType": "portal"
  },
  {
    "id": "aca03cc8-3d5e-5e02-8479-3fb4efda00a8",
    "dataType": "wifi",
    "dataSource": "gov-data",
    "category": "大眾運輸節點",
    "name": "臺鐵局高雄站第1月台4車",
    "lat": 22.63962,
    "lng": 120.302109,
    "address": "807高雄市三民區建國二路318號",
    "ssid": "iTaiwan",
    "authType": "portal"
  },
  {
    "id": "4c28c43b-98f1-586f-a180-cda5c0776884",
    "dataType": "wifi",
    "dataSource": "gov-data",
    "category": "大眾運輸節點",
    "name": "臺鐵局高雄站第1月台7車",
    "lat": 22.63962,
    "lng": 120.302109,
    "address": "807高雄市三民區建國二路318號",
    "ssid": "iTaiwan",
    "authType": "portal"
  },
  {
    "id": "931b5c5b-2781-57d5-b758-002742108455",
    "dataType": "wifi",
    "dataSource": "gov-data",
    "category": "大眾運輸節點",
    "name": "臺鐵局高雄站第2月台5車",
    "lat": 22.63962,
    "lng": 120.302109,
    "address": "807高雄市三民區建國二路318號",
    "ssid": "iTaiwan",
    "authType": "portal"
  }
]
