[
  {
    "id": "71779cc0-4de5-52b0-a24e-04ce97edd22d",
    "dataType": "wifi",
    "dataSource": "gov-data",
    "category": "洽公場所",
    "name": "臺灣南投地方法院檢察署1F單一窗口服務中心",
    "lat": 23.900429,
    "lng": 120.686934,
    "address": "540南投縣南投市中興路757號",
    "ssid": "iTaiwan",
    "authType": "portal"
  },
  {
    "id": "6ca21952-b836-5185-bd5e-bfb3cb0bdf7a",
    "dataType": "wifi",
    "dataSource": "gov-data",
    "category": "洽公場所",
    "name": "臺灣南投地方法院1F庭園候審區",
    "lat": 23.900736,
    "lng": 120.688762,
    "address": "540南投縣南投市中興路759號",
    "ssid": "iTaiwan",
    "authType": "portal"
  },
  {
    "id": "1d4e0a55-2f6e-5ea5-bbf1-b1e75e8958d3",
    "dataType": "wifi",
    "dataSource": "gov-data",
    "category": "洽公場所",
    "name": "司法院(南投地方法院)",
    "lat": 23.901001,
    "lng": 120.688753,
    "address": "540南投縣南投市中興路759號",
    "ssid": "iTaiwan",
    "authType": "portal"
  },
  {
    "id": "1a28b7c0-78c3-5ce7-8703-fef39375c8a9",
    "dataType": "wifi",
    "dataSource": "gov-data",
    "category": "其他",
    "name": "社團法人南投縣三塊厝愛鄉協會",
    "lat": 23.901343,
    "lng": 120.684814,
    "address": "540南投縣南投市三興里大庄路305巷12號(天明宮前廣場)",
    "ssid": "iTaiwan",
    "authType": "portal"
  },
  {
    "id": "4d3dce72-d3c5-59d6-ad80-910440776062",
    "dataType": "wifi",
    "dataSource": "gov-data",
    "category": "洽公場所",
    "name": "財政部中區國稅局南投縣分局",
    "lat": 23.901963,
    "lng": 120.688832,
    "address": "540南投縣南投市復興路2號4樓",
    "ssid": "iTaiwan",
    "authType": "portal"
  },
  {
    "id": "adab36d5-51a5-553c-aa25-60fb410215eb",
    "dataType": "wifi",
    "dataSource": "gov-data",
    "category": "洽公場所",
    "name": "南投縣政府B棟2樓會議室",
    "lat": 23.902053,
    "lng": 120.689857,
    "address": "540南投縣南投市中興路660號",
    "ssid": "iTaiwan",
    "authType": "portal"
  },
  {
    "id": "50085dec-5277-5c98-90ca-9d76b93b6242",
    "dataType": "wifi",
    "dataSource": "gov-data",
    "category": "洽公場所",
    "name": "南投縣政府B棟2樓建設處服務台",
    "lat": 23.902239,
    "lng": 120.690647,
    "address": "540南投縣南投市中興路660號",
    "ssid": "iTaiwan",
    "authType": "portal"
  },
  {
    "id": "88f15f39-ca47-5bbd-9b97-ca21e99a94d1",
    "dataType": "wifi",
    "dataSource": "gov-data",
    "category": "洽公場所",
    "name": "南投縣政府服務中心",
    "lat": 23.902533,
    "lng": 120.690694,
    "address": "540南投縣南投市中興路660號",
    "ssid": "iTaiwan",
    "authType": "portal"
  },
  {
    "id": "a7e385dc-8668-5d11-a2cb-17e6c0341143",
    "dataType": "wifi",
    "dataSource": "gov-data",
    "category": "洽公場所",
    "name": "南投縣政府A棟5樓會議室",
    "lat": 23.902533,
    "lng": 120.690694,
    "address": "540南投縣南投市中興路660號",
    "ssid": "iTaiwan",
    "authType": "portal"
  },
  {
    "id": "950dfad8-c70a-525f-9216-126e4a0909be",
    "dataType": "wifi",
    "dataSource": "gov-data",
    "category": "洽公場所",
    "name": "南投縣政府A棟7樓國際會議廳",
    "lat": 23.902583,
    "lng": 120.690497,
    "address": "540南投縣南投市中興路660號",
    "ssid": "iTaiwan",
    "authType": "portal"
  },
  {
    "id": "2d70d77e-e8f8-5757-919e-34fa78d013be",
    "dataType": "wifi",
    "dataSource": "gov-data",
    "category": "洽公場所",
    "name": "南投縣政府縣民廣場",
    "lat": 23.902602,
    "lng": 120.689578,
    "address": "540南投縣南投市中興路660號",
    "ssid": "iTaiwan",
    "authType": "portal"
  },
  {
    "id": "12d9576c-c94e-5d3c-a7e2-d38b40f6157a",
    "dataType": "wifi",
    "dataSource": "gov-data",
    "category": "洽公場所",
    "name": "南投縣政府環境保護局",
    "lat": 23.902624,
    "lng": 120.690478,
    "address": "540南投縣南投市中興路660號c棟2、3樓",
    "ssid": "iTaiwan",
    "authType": "portal"
  },
  {
    "id": "2f39d245-ee02-51ea-ae29-c317612ae52d",
    "dataType": "wifi",
    "dataSource": "gov-data",
    "category": "洽公場所",
    "name": "南投縣政府衛生局",
    "lat": 23.902749,
    "lng": 120.688527,
    "address": "540南投縣南投市復興路6號",
    "ssid": "iTaiwan",
    "authType": "portal"
  },
  {
    "id": "1cc7a7c7-8744-562a-bf40-14332e414888",
    "dataType": "wifi",
    "dataSource": "gov-data",
    "category": "文教館所",
    "name": "南投縣政府文化局圖書館",
    "lat": 23.90293,
    "lng": 120.691337,
    "address": "540南投縣南投市中興路669號",
    "ssid": "iTaiwan",
    "authType": "portal"
  },
  {
    "id": "2b124f22-3d03-598b-8fce-674ffbf9173b",
    "dataType": "wifi",
    "dataSource": "gov-data",
    "category": "其他",
    "name": "社團法人南投縣青年返鄉服務協會",
    "lat": 23.903439,
    "lng": 120.689612,
    "address": "540南投縣南投市三和里24鄰三和一路8號",
    "ssid": "iTaiwan",
    "authType": "portal"
  },
  {
    "id": "55b55876-15e1-5a9a-9eca-aefa3f203a33",
    "dataType": "wifi",
    "dataSource": "gov-data",
    "category": "洽公場所",
    "name": "南投縣風景區管理所",
    "lat": 23.903741,
    "lng": 120.689602,
    "address": "540南投縣南投市三和一路8號",
    "ssid": "iTaiwan",
    "authType": "portal"
  },
  {
    "id": "2b01a28a-e725-55fc-b631-fbc8845a1475",
    "dataType": "wifi",
    "dataSource": "gov-data",
    "category": "洽公場所",
    "name": "南投縣綜合大樓",
    "lat": 23.904083,
    "lng": 120.689396,
    "address": "540南投縣南投市三和一路8號",
    "ssid": "iTaiwan",
    "authType": "portal"
  },
  {
    "id": "3a37835f-66c1-57cd-9f13-88d5499ad214",
    "dataType": "wifi",
    "dataSource": "gov-data",
    "category": "洽公場所",
    "name": "南投縣綜合大樓電腦教室",
    "lat": 23.904083,
    "lng": 120.689396,
    "address": "540南投縣南投市三和一路8號",
    "ssid": "iTaiwan",
    "authType": "portal"
  },
  {
    "id": "f600ddc5-8acc-50e5-b6d2-547eabd355a1",
    "dataType": "wifi",
    "dataSource": "gov-data",
    "category": "洽公場所",
    "name": "南投縣南投地政事務所",
    "lat": 23.904142,
    "lng": 120.687046,
    "address": "540南投縣南投市三和二路60號",
    "ssid": "iTaiwan",
    "authType": "portal"
  },
  {
    "id": "3429dc78-960f-5bce-9103-9b01ab4720f3",
    "dataType": "wifi",
    "dataSource": "gov-data",
    "category": "洽公場所",
    "name": "南投三和郵局",
    "lat": 23.904367,
    "lng": 120.688465,
    "address": "540南投縣南投市三和二路30號",
    "ssid": "iTaiwan",
    "authType": "portal"
  },
  {
    "id": "46b1934a-4853-590a-b48e-efae124da501",
    "dataType": "wifi",
    "dataSource": "gov-data",
    "category": "洽公場所",
    "name": "臺灣銀行南投分行",
    "lat": 23.904698,
    "lng": 120.687483,
    "address": "540南投縣南投市復興路101號",
    "ssid": "iTaiwan",
    "authType": "portal"
  },
  {
    "id": "43491b77-2e39-501f-bd73-d40356f6a559",
    "dataType": "wifi",
    "dataSource": "gov-data",
    "category": "其他",
    "name": "財團法人中華民國佛教慈濟慈善事業基金會(南投)",
    "lat": 23.906253,
    "lng": 120.692787,
    "address": "540南投縣南投市振興里果稟路101號",
    "ssid": "iTaiwan",
    "authType": "portal"
  },
  {
    "id": "f6e940b5-fc67-525d-95db-8794d9248c68",
    "dataType": "wifi",
    "dataSource": "gov-data",
    "category": "洽公場所",
    "name": "國軍退除役官兵輔導委員會南投縣榮民服務處一樓大廳",
    "lat": 23.906642,
    "lng": 120.680596,
    "address": "540南投縣南投市民族路505號",
    "ssid": "iTaiwan",
    "authType": "portal"
  },
  {
    "id": "a1872fa7-7455-5ca0-a25b-42dae46365bd",
    "dataType": "wifi",
    "dataSource": "gov-data",
    "category": "洽公場所",
    "name": "中油公司南投縣南投市南投三和站",
    "lat": 23.906699,
    "lng": 120.690651,
    "address": "540南投縣南投市三和里中興路549號",
    "ssid": "iTaiwan",
    "authType": "portal"
  },
  {
    "id": "1e6ba00a-ca36-5b78-8a85-60c365b790cd",
    "dataType": "wifi",
    "dataSource": "gov-data",
    "category": "其他",
    "name": "南投基督教醫院(南投教會亞設學苑)",
    "lat": 23.906843,
    "lng": 120.686325,
    "address": "540南投縣南投市崇文里中山街79號",
    "ssid": "iTaiwan",
    "authType": "portal"
  },
  {
    "id": "c3ef6d53-c835-552a-a71f-8de254201123",
    "dataType": "wifi",
    "dataSource": "gov-data",
    "category": "其他",
    "name": "社團法人南投縣南投市芳美社區發展協會",
    "lat": 23.9071,
    "lng": 120.6963,
    "address": "540南投縣南投市振興里振興巷47弄1號",
    "ssid": "iTaiwan",
    "authType": "portal"
  },
  {
    "id": "148dc8ef-a920-51c7-8d7a-16b1827f2e7d",
    "dataType": "wifi",
    "dataSource": "gov-data",
    "category": "洽公場所",
    "name": "內政部移民署南投縣服務站(新)",
    "lat": 23.907144,
    "lng": 120.685803,
    "address": "540南投縣南投市文昌街87號1樓",
    "ssid": "iTaiwan",
    "authType": "portal"
  },
  {
    "id": "bd0ac2b2-b25e-5e4a-bb31-ea880143cc32",
    "dataType": "wifi",
    "dataSource": "gov-data",
    "category": "洽公場所",
    "name": "南投縣後備指揮部",
    "lat": 23.907278,
    "lng": 120.68302,
    "address": "540南投縣南投市民族路512號",
    "ssid": "iTaiwan",
    "authType": "portal"
  },
  {
    "id": "008a8252-705d-5987-b17b-108b0b15d2cb",
    "dataType": "wifi",
    "dataSource": "gov-data",
    "category": "洽公場所",
    "name": "兆豐國際商銀南投分行",
    "lat": 23.907366,
    "lng": 120.687741,
    "address": "540南投縣南投市文昌街45號",
    "ssid": "iTaiwan",
    "authType": "portal"
  },
  {
    "id": "002c77e6-9e68-5635-8fd8-29dffaf5eccc",
    "dataType": "wifi",
    "dataSource": "gov-data",
    "category": "旅遊景點",
    "name": "南投縣心理衛生中心",
    "lat": 23.907369,
    "lng": 120.687744,
    "address": "540南投縣南投市文昌街45號4樓",
    "ssid": "iTaiwan",
    "authType": "portal"
  },
  {
    "id": "55e4bb1b-09f1-534a-b12c-b0d540ca3647",
    "dataType": "wifi",
    "dataSource": "gov-data",
    "category": "洽公場所",
    "name": "華南商業銀行南投分行",
    "lat": 23.908477,
    "lng": 120.686874,
    "address": "540南投縣南投市復興路236號",
    "ssid": "iTaiwan",
    "authType": "portal"
  },
  {
    "id": "0470b899-de82-51c0-9982-3ef5309fa231",
    "dataType": "wifi",
    "dataSource": "gov-data",
    "category": "其他",
    "name": "南投縣南投市三民社區發展協會",
    "lat": 23.909268,
    "lng": 120.683292,
    "address": "540南投縣南投市三民里民生街33之3號二樓(南投市市區七里-里民活動中心)",
    "ssid": "iTaiwan",
    "authType": "portal"
  },
  {
    "id": "5a827467-8365-5f8a-8023-9ca117b16000",
    "dataType": "wifi",
    "dataSource": "gov-data",
    "category": "文教館所",
    "name": "南投縣政府文化局縣史館",
    "lat": 23.909487,
    "lng": 120.684298,
    "address": "540南投縣南投市彰南路二段65號",
    "ssid": "iTaiwan",
    "authType": "portal"
  },
  {
    "id": "6483f40e-08b0-593f-80c7-4f7c4aec4de0",
    "dataType": "wifi",
    "dataSource": "gov-data",
    "category": "洽公場所",
    "name": "臺灣土地銀行南投分行",
    "lat": 23.910014,
    "lng": 120.685425,
    "address": "540南投縣南投市中山街202號",
    "ssid": "iTaiwan",
    "authType": "portal"
  },
  {
    "id": "4df33e8b-8f36-5772-b051-ee9125d81411",
    "dataType": "wifi",
    "dataSource": "gov-data",
    "category": "其他",
    "name": "南投好厝邊銀髮健身俱樂部",
    "lat": 23.91004,
    "lng": 120.69184,
    "address": "540南投縣南投市信義街5巷26號",
    "ssid": "iTaiwan",
    "authType": "portal"
  },
  {
    "id": "9ba55deb-3578-5e36-a888-a02c525e55a0",
    "dataType": "wifi",
    "dataSource": "gov-data",
    "category": "其他",
    "name": "家照-家照好厝邊失智社區服務據點",
    "lat": 23.910043,
    "lng": 120.691844,
    "address": "540南投縣南投市平和里信義街5巷26號",
    "ssid": "iTaiwan",
    "authType": "portal"
  },
  {
    "id": "cca87354-66e9-5ad6-8106-657f67673d01",
    "dataType": "wifi",
    "dataSource": "gov-data",
    "category": "其他",
    "name": "社團法人南投縣家庭照顧者關懷協會(平山里)",
    "lat": 23.910044,
    "lng": 120.691718,
    "address": "540南投縣南投市龍泉里信義街5巷26號",
    "ssid": "iTaiwan",
    "authType": "portal"
  },
  {
    "id": "20b93f4f-3636-50f9-9dc5-c32f318a36b9",
    "dataType": "wifi",
    "dataSource": "gov-data",
    "category": "其他",
    "name": "南投縣左岸成長學苑關懷協會",
    "lat": 23.910104,
    "lng": 120.685815,
    "address": "540南投縣南投市仁和里民生街33之3號一樓",
    "ssid": "iTaiwan",
    "authType": "portal"
  },
  {
    "id": "f9654480-5976-5bb2-8222-2fc89d18e0f0",
    "dataType": "wifi",
    "dataSource": "gov-data",
    "category": "洽公場所",
    "name": "南投民族路郵局",
    "lat": 23.910151,
    "lng": 120.691715,
    "address": "540南投縣南投市民族路91、93號",
    "ssid": "iTaiwan",
    "authType": "portal"
  },
  {
    "id": "adcd75e6-7097-5443-ab8b-0c1967e061d0",
    "dataType": "wifi",
    "dataSource": "gov-data",
    "category": "其他",
    "name": "社團法人南投縣失智者關懷協會",
    "lat": 23.910249,
    "lng": 120.686158,
    "address": "540南投縣南投市仁和里民生街33號四樓",
    "ssid": "iTaiwan",
    "authType": "portal"
  },
  {
    "id": "50d8a1a8-46b9-5727-8a54-66c369e949af",
    "dataType": "wifi",
    "dataSource": "gov-data",
    "category": "洽公場所",
    "name": "南投縣政府警察局南投分局南投派出所",
    "lat": 23.910262,
    "lng": 120.68327,
    "address": "540南投縣南投市彰南路二段109號",
    "ssid": "iTaiwan",
    "authType": "portal"
  },
  {
    "id": "3680d453-be12-5433-ba06-73333f385585",
    "dataType": "wifi",
    "dataSource": "gov-data",
    "category": "洽公場所",
    "name": "勞動部勞動力發展署中彰投分署南投就業中心洽公櫃台",
    "lat": 23.91032,
    "lng": 120.683042,
    "address": "540南投縣南投市彰南路二段117號",
    "ssid": "iTaiwan",
    "authType": "portal"
  },
  {
    "id": "3f5b553e-582e-5d7b-b067-459f5289e439",
    "dataType": "wifi",
    "dataSource": "gov-data",
    "category": "洽公場所",
    "name": "第一商業銀行(南投分行)",
    "lat": 23.910377,
    "lng": 120.684551,
    "address": "540南投縣南投市中山一街2號",
    "ssid": "iTaiwan",
    "authType": "portal"
  },
  {
    "id": "d179d4a9-6fad-5055-aa7d-bad556065df2",
    "dataType": "wifi",
    "dataSource": "gov-data",
    "category": "洽公場所",
    "name": "勞動部勞動力發展署中彰投分署南投就業中心3F",
    "lat": 23.910488,
    "lng": 120.683023,
    "address": "540南投縣南投市彰南路二段117號",
    "ssid": "iTaiwan",
    "authType": "portal"
  },
  {
    "id": "1a2e7765-cfff-5129-94c5-429ddf74adb5",
    "dataType": "wifi",
    "dataSource": "gov-data",
    "category": "洽公場所",
    "name": "勞動部勞動力發展署中彰投分署南投就業中心4F",
    "lat": 23.910488,
    "lng": 120.683023,
    "address": "540南投縣南投市彰南路二段117號",
    "ssid": "iTaiwan",
    "authType": "portal"
  },
  {
    "id": "080522ba-70aa-528f-bdf4-57c56e22cb17",
    "dataType": "wifi",
    "dataSource": "gov-data",
    "category": "洽公場所",
    "name": "南投中山街郵局",
    "lat": 23.910518,
    "lng": 120.683924,
    "address": "540南投縣南投市三民里中山街259號",
    "ssid": "iTaiwan",
    "authType": "portal"
  },
  {
    "id": "d76daf30-8210-54c7-8bef-76d286bd1236",
    "dataType": "wifi",
    "dataSource": "gov-data",
    "category": "洽公場所",
    "name": "南投縣南投市戶政事務所",
    "lat": 23.910527,
    "lng": 120.689803,
    "address": "540南投縣南投市育樂一街16號",
    "ssid": "iTaiwan",
    "authType": "portal"
  },
  {
    "id": "a8327f0a-5c1d-5a17-b937-0742ab5e19bc",
    "dataType": "wifi",
    "dataSource": "gov-data",
    "category": "洽公場所",
    "name": "南投市民代表會",
    "lat": 23.911419,
    "lng": 120.687319,
    "address": "540南投縣南投市大同街234號",
    "ssid": "iTaiwan",
    "authType": "portal"
  },
  {
    "id": "67e3ca97-4725-5ce5-a1b6-426c1da7c322",
    "dataType": "wifi",
    "dataSource": "gov-data",
    "category": "洽公場所",
    "name": "行政院勞動部勞工保險局南投辦事處洽公櫃台",
    "lat": 23.911487,
    "lng": 120.693611,
    "address": "540南投縣南投市芳美路391號",
    "ssid": "iTaiwan",
    "authType": "portal"
  },
  {
    "id": "60ce500a-b1c1-5181-afe0-e621177b7095",
    "dataType": "wifi",
    "dataSource": "gov-data",
    "category": "洽公場所",
    "name": "南投縣南投市公所",
    "lat": 23.911655,
    "lng": 120.687681,
    "address": "540南投縣南投市玉井街5號",
    "ssid": "iTaiwan",
    "authType": "portal"
  },
  {
    "id": "9132e62d-ef8d-579d-9a82-6b4b2c269e3b",
    "dataType": "wifi",
    "dataSource": "gov-data",
    "category": "公立醫院",
    "name": "南投醫院-1樓門診掛號批價區",
    "lat": 23.913993,
    "lng": 120.684307,
    "address": "540南投縣南投市復興路478號",
    "ssid": "iTaiwan",
    "authType": "portal"
  },
  {
    "id": "81a8d019-c8c9-5647-aa12-eb36a262808f",
    "dataType": "wifi",
    "dataSource": "gov-data",
    "category": "文教館所",
    "name": "南投市立圖書館",
    "lat": 23.914562,
    "lng": 120.680997,
    "address": "540南投縣南投市漳興巷51號",
    "ssid": "iTaiwan",
    "authType": "portal"
  }
]
