[
  {
    "id": "0f735ce2-9d9f-5700-a10b-342e65491195",
    "dataType": "wifi",
    "dataSource": "gov-data",
    "category": "其他",
    "name": "慈聖宮",
    "lat": 24.620742,
    "lng": 120.88972,
    "address": "361苗栗縣造橋鄉大西村8鄰慈聖路二段498巷1弄9號",
    "ssid": "iTaiwan",
    "authType": "portal"
  },
  {
    "id": "3aa4894e-6ae2-5869-bf90-510b0c772473",
    "dataType": "wifi",
    "dataSource": "gov-data",
    "category": "其他",
    "name": "苗栗縣造橋鄉大西社區發展協會",
    "lat": 24.622077,
    "lng": 120.89117,
    "address": "361苗栗縣造橋鄉大西村13鄰大西二街128巷3號",
    "ssid": "iTaiwan",
    "authType": "portal"
  },
  {
    "id": "c3b910ed-543a-5e9e-8cbf-412dd2423512",
    "dataType": "wifi",
    "dataSource": "gov-data",
    "category": "其他",
    "name": "為恭醫療財團法人為恭紀念醫院(造橋鄉據點)",
    "lat": 24.622632,
    "lng": 120.888649,
    "address": "361苗栗縣造橋鄉大西村8鄰慈聖路二段498巷1弄9號",
    "ssid": "iTaiwan",
    "authType": "portal"
  },
  {
    "id": "45e54e1e-132f-57bc-8f59-c1bfacf4f5cc",
    "dataType": "wifi",
    "dataSource": "gov-data",
    "category": "洽公場所",
    "name": "造橋大西郵局",
    "lat": 24.622805,
    "lng": 120.89088,
    "address": "361苗栗縣造橋鄉大西村十字路18號",
    "ssid": "iTaiwan",
    "authType": "portal"
  },
  {
    "id": "fe6dd853-93d5-5fd2-8e3a-3584cbd23b6d",
    "dataType": "wifi",
    "dataSource": "gov-data",
    "category": "其他",
    "name": "銀海社區型職能治療所(造橋)",
    "lat": 24.62321,
    "lng": 120.891303,
    "address": "361苗栗縣造橋鄉大西村大西二街3號",
    "ssid": "iTaiwan",
    "authType": "portal"
  },
  {
    "id": "5b61ae5e-93d8-557c-aaf8-50ab1f3f7ba4",
    "dataType": "wifi",
    "dataSource": "gov-data",
    "category": "其他",
    "name": "苗栗縣頭份市頭份社區發展協會",
    "lat": 24.634,
    "lng": 120.88,
    "address": "351苗栗縣頭份市頭份里顯會路76號",
    "ssid": "iTaiwan",
    "authType": "portal"
  }
]
