[
  {
    "dataType": "wifi",
    "dataSource": "gov-data",
    "category": "洽公場所",
    "name": "造橋郵局",
    "lat": 24.640384,
    "lng": 120.865903,
    "address": "361苗栗縣造橋鄉造橋村平仁路32號",
    "ssid": "iTaiwan",
    "authType": "portal"
  },
  {
    "dataType": "wifi",
    "dataSource": "gov-data",
    "category": "大眾運輸節點",
    "name": "臺鐵局造橋站候車室前方",
    "lat": 24.641855,
    "lng": 120.865035,
    "address": "361苗栗縣造橋鄉造橋村平仁路54號",
    "ssid": "iTaiwan",
    "authType": "portal"
  },
  {
    "dataType": "wifi",
    "dataSource": "gov-data",
    "category": "洽公場所",
    "name": "內政部警政署國道公路警察局第二警察隊",
    "lat": 24.643117,
    "lng": 120.873427,
    "address": "361苗栗縣造橋鄉造橋村雙鵝山9號",
    "ssid": "iTaiwan",
    "authType": "portal"
  },
  {
    "dataType": "wifi",
    "dataSource": "gov-data",
    "category": "洽公場所",
    "name": "苗栗縣造橋鄉戶政事務所",
    "lat": 24.656378,
    "lng": 120.865402,
    "address": "361苗栗縣造橋鄉造橋村13鄰東興5之5號",
    "ssid": "iTaiwan",
    "authType": "portal"
  }
]
